[
    {
        "actionName": "Action",
        "steps": [
            {
                "stepId": "STEP1",
                "stepName": "Url: LoanIQ",
                "infFile": "t1.inf",
                "time": 1772101752233
            },
            {
                "stepId": "STEP2",
                "stepName": "Url: personal.JPG",
                "infFile": "t2.inf",
                "time": 1772101752280
            },
            {
                "stepId": "STEP3",
                "stepName": "Submit Data: Login",
                "infFile": "t3.inf",
                "time": 1772101752388
            },
            {
                "stepId": "STEP4",
                "stepName": "Url: Accounts.JPG",
                "infFile": "t4.inf",
                "time": 1772101752441
            },
            {
                "stepId": "STEP5",
                "stepName": "Url: Account Summary",
                "infFile": "t6.inf",
                "time": 1772101752482
            },
            {
                "stepId": "STEP6",
                "stepName": "Url: Accounts",
                "infFile": "t7.inf",
                "time": 1772101752505
            },
            {
                "stepId": "STEP7",
                "stepName": "Url: Fund Transfer",
                "infFile": "t8.inf",
                "time": 1772101752535
            },
            {
                "stepId": "STEP8",
                "stepName": "Url: Bank to Bank Transfer",
                "infFile": "t9.inf",
                "time": 1772101752561
            },
            {
                "stepId": "STEP9",
                "stepName": "Url: showdet.jsp",
                "infFile": "t10.inf",
                "time": 1772101752601
            },
            {
                "stepId": "STEP10",
                "stepName": "Submit Data: fund1.jsp",
                "infFile": "t11.inf",
                "time": 1772101752632
            },
            {
                "stepId": "STEP11",
                "stepName": "Submit Data: FundTransfer1.jsp",
                "infFile": "t12.inf",
                "time": 1772101752708
            },
            {
                "stepId": "STEP12",
                "stepName": "Submit Data: fundtransferresult.jsp",
                "infFile": "t13.inf",
                "time": 1772101752747
            },
            {
                "stepId": "STEP13",
                "stepName": "Url: logout.JPG",
                "infFile": "t14.inf",
                "time": 1772101752775
            }
        ],
        "transactions": [
            {
                "transactionName": "AB_FundTransfer_T01_Launch",
                "rawStartTime": 1772101751851,
                "rawEndTime": 1772101752235,
                "thinkTime": 0.0,
                "wastedTime": 0.05345892906188965
            },
            {
                "transactionName": "AB_FundTransfer_T02_AccessPersonalBanking",
                "rawStartTime": 1772101752235,
                "rawEndTime": 1772101752280,
                "thinkTime": 0.0,
                "wastedTime": 0.004777193069458008
            },
            {
                "transactionName": "AB_FundTransfer_T03_UserLogin",
                "rawStartTime": 1772101752280,
                "rawEndTime": 1772101752388,
                "thinkTime": 0.0,
                "wastedTime": 0.007336139678955078
            },
            {
                "transactionName": "AB_FundTransfer_T04_SelectAccount",
                "rawStartTime": 1772101752388,
                "rawEndTime": 1772101752441,
                "thinkTime": 0.0,
                "wastedTime": 0.004143476486206055
            },
            {
                "transactionName": "AB_FundTransfer_T05_ViewAccountSummary",
                "rawStartTime": 1772101752441,
                "rawEndTime": 1772101752482,
                "thinkTime": 0.0,
                "wastedTime": 0.005057573318481445
            },
            {
                "transactionName": "AB_FundTransfer_T06_SelectAccountAgain",
                "rawStartTime": 1772101752482,
                "rawEndTime": 1772101752505,
                "thinkTime": 0.0,
                "wastedTime": 0.0029778480529785158
            },
            {
                "transactionName": "AB_FundTransfer_T07_SelectFundTransfer",
                "rawStartTime": 1772101752505,
                "rawEndTime": 1772101752536,
                "thinkTime": 0.0,
                "wastedTime": 0.0038902759552001955
            },
            {
                "transactionName": "AB_FundTransfer_T08_SelectBankToBankTransfer",
                "rawStartTime": 1772101752536,
                "rawEndTime": 1772101752561,
                "thinkTime": 0.0,
                "wastedTime": 0.003700733184814453
            },
            {
                "transactionName": "AB_FundTransfer_T09_AccountReview",
                "rawStartTime": 1772101752561,
                "rawEndTime": 1772101752601,
                "thinkTime": 0.0,
                "wastedTime": 0.004292726516723633
            },
            {
                "transactionName": "AB_FundTransfer_T10_SubmitAccount",
                "rawStartTime": 1772101752601,
                "rawEndTime": 1772101752632,
                "thinkTime": 0.0,
                "wastedTime": 0.0033512115478515627
            },
            {
                "transactionName": "AB_FundTransfer_T11_PayAmount",
                "rawStartTime": 1772101752632,
                "rawEndTime": 1772101752747,
                "thinkTime": 0.0,
                "wastedTime": 0.008360862731933594
            },
            {
                "transactionName": "AB_FundTransfer_T12_UserLogout",
                "rawStartTime": 1772101752747,
                "rawEndTime": 1772101752776,
                "thinkTime": 0.0,
                "wastedTime": 0.00475311279296875
            }
        ]
    }
]